LICENSE
README.rst
setup.py
ipwhois/IPwhois.py
ipwhois/__init__.py
kamabay_ipwhois.egg-info/PKG-INFO
kamabay_ipwhois.egg-info/SOURCES.txt
kamabay_ipwhois.egg-info/dependency_links.txt
kamabay_ipwhois.egg-info/entry_points.txt
kamabay_ipwhois.egg-info/requires.txt
kamabay_ipwhois.egg-info/top_level.txt