Metadata-Version: 1.1
Name: kamabay-ipwhois
Version: 0.1.0
Summary: ip information gathering.
Home-page: https://github.com/ExsoKamabay/ipwhois
Author: Exso Kamabay
Author-email: UNKNOWN
License: Apache License 2.0
Keywords: kamabay,ip,whois,information,gathering
Platform: UNKNOWN
Classifier: License :: OSI Approved :: Apache Software License
Classifier: Operating System :: OS Independent
Classifier: Programming Language :: Python :: 3
Classifier: Topic :: Utilities
